{
  "gpu": "NVIDIA RTX 4000 Ada Generation",
  "model": "deit_base_patch16_224",
  "fixed_ratio": 0.5,
  "batch_sizes": [
    1,
    8,
    32,
    128
  ],
  "padded": {
    "1": {
      "front_early_ms": 0.54,
      "gather_ms": 0.063,
      "late_blocks_ms": 1.162,
      "head_ms": 0.029
    },
    "8": {
      "front_early_ms": 2.324,
      "gather_ms": 0.279,
      "late_blocks_ms": 5.243,
      "head_ms": 0.033
    },
    "32": {
      "front_early_ms": 9.381,
      "gather_ms": 1.022,
      "late_blocks_ms": 22.872,
      "head_ms": 0.032
    },
    "128": {
      "front_early_ms": 38.995,
      "gather_ms": 3.975,
      "late_blocks_ms": 97.299,
      "head_ms": 0.032
    }
  },
  "triton": {
    "1": {
      "front_early_ms": 0.54,
      "pack_ms": 0.077,
      "late_blocks_ms": 1.152,
      "head_ms": 0.04
    },
    "8": {
      "front_early_ms": 2.324,
      "pack_ms": 0.077,
      "late_blocks_ms": 2.096,
      "head_ms": 0.039
    },
    "32": {
      "front_early_ms": 9.381,
      "pack_ms": 0.083,
      "late_blocks_ms": 8.694,
      "head_ms": 0.038
    },
    "128": {
      "front_early_ms": 38.995,
      "pack_ms": 0.09,
      "late_blocks_ms": 34.7,
      "head_ms": 0.037
    }
  }
}